<?xml version="1.0"?>
<opencv_storage>
<stage1>
  <maxWeakCount>6</maxWeakCount>
  <stageThreshold>-3.7084597349166870e-01</stageThreshold>
  <weakClassifiers>
    <_>
      <internalNodes>
        0 -1 28510 3.5606853663921356e-02</internalNodes>
      <leafValues>
        -1.3609467446804047e-01 9.3893128633499146e-01</leafValues></_>
    <_>
      <internalNodes>
        0 -1 113756 -7.1841189637780190e-03</internalNodes>
      <leafValues>
        -9.0462434291839600e-01 3.5453408956527710e-01</leafValues></_>
    <_>
      <internalNodes>
        0 -1 109353 -5.9076361358165741e-02</internalNodes>
      <leafValues>
        9.3727076053619385e-01 -2.7105227112770081e-01</leafValues></_>
    <_>
      <internalNodes>
        0 -1 17226 -4.0128178894519806e-02</internalNodes>
      <leafValues>
        3.9685907959938049e-01 -5.7707357406616211e-01</leafValues></_>
    <_>
      <internalNodes>
        0 -1 49284 -1.5166181139647961e-02</internalNodes>
      <leafValues>
        7.9451370239257813e-01 -3.0787777900695801e-01</leafValues></_>
    <_>
      <internalNodes>
        0 -1 150739 2.3515180218964815e-03</internalNodes>
      <leafValues>
        -3.5497897863388062e-01 5.6671828031539917e-01</leafValues></_></weakClassifiers></stage1>
</opencv_storage>
